camera_stage_mapping/__init__.py
camera_stage_mapping/array_with_attrs.py
camera_stage_mapping/camera_stage_calibration_1d.py
camera_stage_mapping/camera_stage_calibration_2d.py
camera_stage_mapping/camera_stage_tracker.py
camera_stage_mapping/closed_loop_move.py
camera_stage_mapping/correlation_image_tracking.py
camera_stage_mapping/exceptions.py
camera_stage_mapping/fft_image_tracking.py
camera_stage_mapping/scan_coords_times.py
camera_stage_mapping-0.1.10.dist-info/licenses/LICENSE
camera_stage_mapping-0.1.10.dist-info/METADATA
camera_stage_mapping-0.1.10.dist-info/WHEEL
camera_stage_mapping-0.1.10.dist-info/top_level.txt
camera_stage_mapping-0.1.10.dist-info/RECORD
