Metadata-Version: 2.4
Name: camera-stage-mapping
Version: 0.1.10
Summary: Calibration and mapping between stage and camera coordinates in a microscope
Author-email: Richard Bowman <richard.bowman@cantab.net>
License-Expression: LGPL-3.0-or-later
Project-URL: homepage, https://gitlab.com/openflexure/microscope-extensions/camera-stage-mapping/
Requires-Python: >=3.9
License-File: LICENSE
Requires-Dist: numpy>=2.0
Provides-Extra: correlation
Requires-Dist: opencv-python-headless>=4.1; extra == "correlation"
Requires-Dist: scipy>=1.4; extra == "correlation"
Provides-Extra: ofmclient
Requires-Dist: openflexure-microscope-client; extra == "ofmclient"
Provides-Extra: ipython
Requires-Dist: ipykernel; extra == "ipython"
Requires-Dist: matplotlib; extra == "ipython"
Provides-Extra: all
Requires-Dist: opencv-python-headless>=4.1; extra == "all"
Requires-Dist: scipy>=1.4; extra == "all"
Requires-Dist: openflexure-microscope-client; extra == "all"
Requires-Dist: ipykernel; extra == "all"
Requires-Dist: matplotlib; extra == "all"
Provides-Extra: dev
Requires-Dist: build; extra == "dev"
Requires-Dist: twine; extra == "dev"
Requires-Dist: pytest>=7.4; extra == "dev"
Requires-Dist: matplotlib>=3.2; extra == "dev"
Requires-Dist: sphinx>=8.0; extra == "dev"
Requires-Dist: sphinx-rtd-theme>=3.0; extra == "dev"
Requires-Dist: sphinx-autoapi>=3.1; extra == "dev"
Dynamic: license-file
